mygraphtools
