Metadata-Version: 1.2
Name: mygraphtools
Version: 1.2.1
Summary: Uma biblioteca para trabalhar com grafos de maneira simples
Home-page: https://github.com/gabrielsoutoabreu/mygraphtools
Author: Gabriel Souto
Author-email: ga.vs_@outlook.com
License: MIT
Project-URL: Código fonte, https://github.com/gabrielsoutoabreu/mygraphtools
Project-URL: Download, https://github.com/gabrielsoutoabreu/mygraphtools/archive/main.zip
Keywords: grafos graphs
Platform: UNKNOWN
